sandinvest/__init__.py
sandinvest/__version__.py
sandinvest/api.py
sandinvest/client.py
sandinvest/error.py
sandinvest/fields.py
sandinvest/utils.py
SandInvest-0.5.0.dist-info/METADATA
SandInvest-0.5.0.dist-info/WHEEL
SandInvest-0.5.0.dist-info/top_level.txt
SandInvest-0.5.0.dist-info/RECORD
