Metadata-Version: 2.1
Name: SandInvest
Version: 0.5.0
Summary: SandInvest是一款专注于量化开发的金融数据接口，开始体验吧！
Home-page: UNKNOWN
Author: SandQuant
Author-email: data@sandquant.com
License: UNKNOWN
Keywords: SandInvest,Data API
Platform: UNKNOWN
Classifier: Development Status :: 4 - Beta
Classifier: Intended Audience :: Developers
Classifier: Natural Language :: Chinese (Simplified)
Classifier: Operating System :: OS Independent
Classifier: Programming Language :: Python :: 3.7
Requires-Python: >=3.7
Requires-Dist: pandas
Requires-Dist: requests
